spotify_playlist_transfer/__init__.py
spotify_playlist_transfer/cli.py
spotify_playlist_transfer/utils.py
spotify_playlist_transfer/tests/__init__.py
spotify_playlist_transfer/tests/conftest.py
spotify_playlist_transfer/tests/test_cli.py
spotify_playlist_transfer/tests/test_utils.py
spotify_playlist_transfer-0.1.2.dist-info/METADATA
spotify_playlist_transfer-0.1.2.dist-info/WHEEL
spotify_playlist_transfer-0.1.2.dist-info/entry_points.txt
spotify_playlist_transfer-0.1.2.dist-info/top_level.txt
spotify_playlist_transfer-0.1.2.dist-info/RECORD
