Metadata-Version: 2.2
Name: spotify-playlist-transfer
Version: 0.1.2
Summary: A CLI tool to transfer Spotify playlists and liked songs between accounts
Author-email: Abhishek Kumar Singh <devabhishek81121@gmail.com>
License: MIT
Requires-Python: >=3.9
Requires-Dist: keyring>=25.6.0
Requires-Dist: loguru>=0.7.3
Requires-Dist: python-dotenv>=1.0.1
Requires-Dist: questionary>=2.1.0
Requires-Dist: rich>=13.9.4
Requires-Dist: spotipy>=2.25.1
Requires-Dist: typer>=0.15.2
Provides-Extra: test
Requires-Dist: pytest>=7.0; extra == "test"
Requires-Dist: pytest-mock>=3.10; extra == "test"
Requires-Dist: pytest-cov>=4.0; extra == "test"
Requires-Dist: responses>=0.23; extra == "test"
Requires-Dist: types-requests>=2.28; extra == "test"
Requires-Dist: typer[all]>=0.9.0; extra == "test"
